openepi_client/__init__.py
openepi_client/geocoding/__init__.py
openepi_client/geocoding/_geocoding_client.py
openepi_client/geocoding/_geocoding_types.py
openepi_client/global_forest_watch/__init__.py
openepi_client/global_forest_watch/_create_account.py
openepi_client/global_forest_watch/_create_apikey.py
openepi_client/global_forest_watch/_create_geostore.py
openepi_client/global_forest_watch/_download_asset.py
openepi_client/global_forest_watch/_get_dataset.py
openepi_client/global_forest_watch/_get_fields.py
openepi_client/global_forest_watch/_get_geostore.py
openepi_client/global_forest_watch/_get_version.py
openepi_client/global_forest_watch/_gfw_client.py
openepi_client/global_forest_watch/_gfw_types.py
openepi_client/global_forest_watch/_list_assets.py
openepi_client/global_forest_watch/_list_datasets.py
openepi_client/global_forest_watch/_query.py
openepi_client/global_forest_watch/_query_dataset.py
openepi_client/weather/__init__.py
openepi_client/weather/_weather_client.py
openepi_client/weather/_weather_types.py
openepi_client-2.0.0.dist-info/METADATA
openepi_client-2.0.0.dist-info/WHEEL
openepi_client-2.0.0.dist-info/licenses/LICENSE
openepi_client-2.0.0.dist-info/RECORD
