Metadata-Version: 2.4
Name: openepi-client
Version: 2.0.0
Summary: A python library for interacting with the OpenEPI data
License-Expression: Apache-2.0
License-File: LICENSE
Author: Kenneth Stigen
Author-email: kenneth.stigen@knowit.no
Requires-Python: >=3.12,<4.0
Classifier: Programming Language :: Python :: 3
Classifier: Programming Language :: Python :: 3.12
Classifier: Programming Language :: Python :: 3.13
Classifier: Programming Language :: Python :: 3.14
Requires-Dist: black (>=25.1.0,<26.0.0)
Requires-Dist: geojson-pydantic (>=2.0.0,<3.0.0)
Requires-Dist: httpx (>=0.25.2,<0.26.0)
Requires-Dist: pydantic (>=2.4.2,<3.0.0)
Requires-Dist: pydantic-settings (>=2.0.3,<3.0.0)
Project-URL: Homepage, https://www.openepi.io/
Project-URL: source, https://github.com/openearthplatforminitiative/openepi-client-py
